{"note":"Don't delete this file! It's used internally to help with page regeneration.","name":"Brainfuckrb","body":"## Installation\r\n\r\nIsntall it with RubyGems:\r\n\r\n    $ gem install brainfuckrb\r\n\r\n## Usage\r\n\r\n```ruby\r\n#!/usr/bin/env ruby\r\n# hello_brainfuck.rb\r\n\r\nhello_brainfuck = <<-eos\r\n  ++++++++++[>+++++++>++++++++++>+++>+<<<<-]>++.>+.+++++++..+++.>++.<<+++\r\n  ++++++++++++.>.+++.------.--------.>+.>.\r\neos\r\nbf Brainfuckrb::Brainfuck.new(hello_brainfuck)\r\nbf.run\r\n```\r\n\r\n    $ ./hello_brainfuck.rb\r\n    Hello World!\r\n\r\nOr run brainfuck programs directly:\r\n\r\n    $ brainfuckrb hello.bf\r\n    $ Hello World!\r\n\r\nOnly the brainfuck control characters ```><+-.,[]``` are interpreted.\r\nOthers will be ignored.\r\n\r\n## Known bugs\r\n\r\n* Input does not work\r\n\r\n## Contributing\r\n\r\n1. Fork it\r\n2. Create your feature branch (`git checkout -b my-new-feature`)\r\n3. Commit your changes (`git commit -am 'Added some feature'`)\r\n4. Push to the branch (`git push origin my-new-feature`)\r\n5. Create new Pull Request\r\n","google":"","tagline":"Brainfuck interpreter implemented in Ruby"}